{
  "type": "minecraft:crafting_shaped",
  "category": "misc",
  "key": {
    "#": {
      "item": "minecraft:lapis_lazuli"
    },
    "G": {
      "item": "minecraft:nether_star"
    }
  },
  "pattern": [
    "###",
    "#G#",
    "###"
  ],
  "result": {
    "id": "antithetic:blueorb",
    "components": {
      "minecraft:item_name": "{\"extra\":[{\"color\":\"light_purple\",\"italic\":false,\"text\": \"Blue Orb\"}],\"italic\":false,\"text\":\"\"}",
      "minecraft:lore": [
        "{\"color\":\"gray\",\"text\":\"Returns Kyogre to its Primal State\"}"
      ]
    }
  }
}